apipool/__init__.py
apipool/__init__.pyc
apipool/apikey.py
apipool/apikey.pyc
apipool/manager.py
apipool/manager.pyc
apipool/stats.py
apipool/stats.pyc
apipool/__pycache__/__init__.cpython-34.pyc
apipool/__pycache__/__init__.cpython-35.pyc
apipool/__pycache__/__init__.cpython-36.pyc
apipool/__pycache__/apikey.cpython-34.pyc
apipool/__pycache__/apikey.cpython-35.pyc
apipool/__pycache__/apikey.cpython-36.pyc
apipool/__pycache__/manager.cpython-34.pyc
apipool/__pycache__/manager.cpython-35.pyc
apipool/__pycache__/manager.cpython-36.pyc
apipool/__pycache__/stats.cpython-34.pyc
apipool/__pycache__/stats.cpython-35.pyc
apipool/__pycache__/stats.cpython-36.pyc
apipool/tests/__init__.py
apipool/tests/__init__.pyc
apipool/tests/__pycache__/__init__.cpython-34.pyc
apipool/tests/__pycache__/__init__.cpython-35.pyc
apipool/tests/__pycache__/__init__.cpython-36.pyc
apipool-0.0.2.dist-info/METADATA
apipool-0.0.2.dist-info/RECORD
apipool-0.0.2.dist-info/WHEEL
apipool-0.0.2.dist-info/top_level.txt
